<?xml version="1.0"?>
<pdfxml Title="Biopharm Asia, Inc., China Organic Agriculture, Inc., and Guilin Paper, Inc." CreationDate="D:20130419062631-04'00'" Producer="iTextSharp 5.2.1 (c) 1T3XT BVBA" Keywords="Date: 2013-04-19" Author="U.S. Securities and Exchange Commission" ModDate="D:20130419062631-04'00'" Subject="Order of Suspension of Trading">
  <LTPage bbox="[0, 0, 612, 792]" height="792" pageid="1" rotate="0" width="612" x0="0" x1="612" y0="0" y1="792" page_index="0" page_label="">
    <LTFigure bbox="[0, 0, 612, 792]" height="792" matrix="[1, 0, 0, 1, 0, 0]" name="Xf1" width="612" x0="0" x1="612" y0="0" y1="792">
      <LTTextLineHorizontal bbox="[90.024, 706.368, 93.024, 717.084]" height="10.716" width="3.0" word_margin="0.1" x0="90.024" x1="93.024" y0="706.368" y1="717.084">
        <LTTextBoxHorizontal bbox="[90.024, 706.368, 93.024, 717.084]" height="10.716" index="0" width="3.0" x0="90.024" x1="93.024" y0="706.368" y1="717.084"> </LTTextBoxHorizontal>
      </LTTextLineHorizontal>
      <LTTextLineHorizontal bbox="[218.93, 706.368, 398.95, 717.084]" height="10.716" width="180.02" word_margin="0.1" x0="218.93" x1="398.95" y0="706.368" y1="717.084">
        <LTTextBoxHorizontal bbox="[218.93, 706.368, 398.95, 717.084]" height="10.716" index="1" width="180.02" x0="218.93" x1="398.95" y0="706.368" y1="717.084">UNITED STATES OF AMERICA </LTTextBoxHorizontal>
      </LTTextLineHorizontal>
      <LTTextLineHorizontal bbox="[279.53, 692.548, 335.47, 703.264]" height="10.716" width="55.94" word_margin="0.1" x0="279.53" x1="335.47" y0="692.548" y1="703.264">
        <LTTextBoxHorizontal bbox="[279.53, 692.548, 335.47, 703.264]" height="10.716" index="2" width="55.94" x0="279.53" x1="335.47" y0="692.548" y1="703.264">Before the </LTTextBoxHorizontal>
      </LTTextLineHorizontal>
      <LTTextLineHorizontal bbox="[176.78, 678.748, 438.19, 689.464]" height="10.716" width="261.41" word_margin="0.1" x0="176.78" x1="438.19" y0="678.748" y1="689.464">
        <LTTextBoxHorizontal bbox="[176.78, 678.748, 438.19, 689.464]" height="10.716" index="3" width="261.41" x0="176.78" x1="438.19" y0="678.748" y1="689.464">SECURITIES AND EXCHANGE COMMISSION </LTTextBoxHorizontal>
      </LTTextLineHorizontal>
      <LTTextLineHorizontal bbox="[269.81, 664.948, 345.19, 675.664]" height="10.716" width="75.38" word_margin="0.1" x0="269.81" x1="345.19" y0="664.948" y1="675.664">
        <LTTextBoxHorizontal bbox="[269.81, 664.948, 345.19, 675.664]" height="10.716" index="4" width="75.38" x0="269.81" x1="345.19" y0="664.948" y1="675.664">April 19, 2013 </LTTextBoxHorizontal>
      </LTTextLineHorizontal>
      <LTTextLineHorizontal bbox="[90.024, 645.148, 345.07, 655.864]" height="10.716" width="255.046" word_margin="0.1" x0="90.024" x1="345.07" y0="645.148" y1="655.864">
        <LTTextBoxHorizontal bbox="[90.024, 645.148, 345.07, 655.864]" height="10.716" index="5" width="255.046" x0="90.024" x1="345.07" y0="645.148" y1="655.864">__________________________________________ </LTTextBoxHorizontal>
      </LTTextLineHorizontal>
      <LTTextLineHorizontal bbox="[90.024, 625.588, 93.024, 636.304]" height="10.716" width="3.0" word_margin="0.1" x0="90.024" x1="93.024" y0="625.588" y1="636.304">
        <LTTextBoxHorizontal bbox="[90.024, 625.588, 93.024, 636.304]" height="10.716" index="6" width="3.0" x0="90.024" x1="93.024" y0="625.588" y1="636.304"> </LTTextBoxHorizontal>
      </LTTextLineHorizontal>
      <LTTextLineHorizontal bbox="[126.02, 625.588, 129.02, 636.304]" height="10.716" width="3.0" word_margin="0.1" x0="126.02" x1="129.02" y0="625.588" y1="636.304">
        <LTTextBoxHorizontal bbox="[126.02, 625.588, 129.02, 636.304]" height="10.716" index="7" width="3.0" x0="126.02" x1="129.02" y0="625.588" y1="636.304"> </LTTextBoxHorizontal>
      </LTTextLineHorizontal>
      <LTTextLineHorizontal bbox="[342.07, 625.588, 348.43, 636.496]" height="10.908" width="6.36" word_margin="0.1" x0="342.07" x1="348.43" y0="625.588" y1="636.496">
        <LTTextBoxHorizontal bbox="[342.07, 625.588, 348.43, 636.496]" height="10.908" index="8" width="6.36" x0="342.07" x1="348.43" y0="625.588" y1="636.496">: </LTTextBoxHorizontal>
      </LTTextLineHorizontal>
      <LTTextLineHorizontal bbox="[378.07, 625.588, 381.07, 636.304]" height="10.716" width="3.0" word_margin="0.1" x0="378.07" x1="381.07" y0="625.588" y1="636.304">
        <LTTextBoxHorizontal bbox="[378.07, 625.588, 381.07, 636.304]" height="10.716" index="9" width="3.0" x0="378.07" x1="381.07" y0="625.588" y1="636.304"> </LTTextBoxHorizontal>
      </LTTextLineHorizontal>
      <LTTextLineHorizontal bbox="[414.07, 625.588, 417.07, 636.304]" height="10.716" width="3.0" word_margin="0.1" x0="414.07" x1="417.07" y0="625.588" y1="636.304">
        <LTTextBoxHorizontal bbox="[414.07, 625.588, 417.07, 636.304]" height="10.716" index="10" width="3.0" x0="414.07" x1="417.07" y0="625.588" y1="636.304"> </LTTextBoxHorizontal>
      </LTTextLineHorizontal>
      <LTTextLineHorizontal bbox="[450.07, 625.588, 453.07, 636.304]" height="10.716" width="3.0" word_margin="0.1" x0="450.07" x1="453.07" y0="625.588" y1="636.304">
        <LTTextBoxHorizontal bbox="[450.07, 625.588, 453.07, 636.304]" height="10.716" index="11" width="3.0" x0="450.07" x1="453.07" y0="625.588" y1="636.304"> </LTTextBoxHorizontal>
      </LTTextLineHorizontal>
      <LTTextLineHorizontal bbox="[486.1, 625.588, 489.1, 636.304]" height="10.716" width="3.0" word_margin="0.1" x0="486.1" x1="489.1" y0="625.588" y1="636.304">
        <LTTextBoxHorizontal bbox="[486.1, 625.588, 489.1, 636.304]" height="10.716" index="12" width="3.0" x0="486.1" x1="489.1" y0="625.588" y1="636.304"> </LTTextBoxHorizontal>
      </LTTextLineHorizontal>
      <LTTextBoxHorizontal bbox="[90.024, 495.358, 504.82, 616.696]" height="121.338" index="16" width="414.796" x0="90.024" x1="504.82" y0="495.358" y1="616.696">:ORDEROFSUSPENSION <LTTextLineHorizontal bbox="[378.07, 605.788, 381.07, 616.504]" height="10.716" width="3.0" word_margin="0.1" x0="378.07" x1="381.07" y0="605.788" y1="616.504"><LTTextBoxHorizontal bbox="[378.07, 605.788, 381.07, 616.504]" height="10.716" index="13" width="3.0" x0="378.07" x1="381.07" y0="605.788" y1="616.504"> </LTTextBoxHorizontal></LTTextLineHorizontal><LTTextLineHorizontal bbox="[378.07, 578.188, 381.07, 588.904]" height="10.716" width="3.0" word_margin="0.1" x0="378.07" x1="381.07" y0="578.188" y1="588.904"><LTTextBoxHorizontal bbox="[378.07, 578.188, 381.07, 588.904]" height="10.716" index="14" width="3.0" x0="378.07" x1="381.07" y0="578.188" y1="588.904"> </LTTextBoxHorizontal></LTTextLineHorizontal><LTTextLineHorizontal bbox="[126.02, 591.988, 129.02, 602.896]" height="10.908" width="3.0" word_margin="0.1" x0="126.02" x1="129.02" y0="591.988" y1="602.896"><LTTextBoxHorizontal bbox="[126.02, 591.988, 129.02, 602.896]" height="10.908" index="15" width="3.0" x0="126.02" x1="129.02" y0="591.988" y1="602.896"> </LTTextBoxHorizontal></LTTextLineHorizontal><LTTextLineHorizontal bbox="[342.07, 605.788, 348.43, 616.696]" height="10.908" width="6.36" word_margin="0.1" x0="342.07" x1="348.43" y0="605.788" y1="616.696">: </LTTextLineHorizontal><LTTextLineHorizontal bbox="[90.024, 605.788, 178.34, 616.504]" height="10.716" width="88.316" word_margin="0.1" x0="90.024" x1="178.34" y0="605.788" y1="616.504">In the Matter of </LTTextLineHorizontal><LTTextLineHorizontal bbox="[342.07, 591.988, 348.43, 602.896]" height="10.908" width="6.36" word_margin="0.1" x0="342.07" x1="348.43" y0="591.988" y1="602.896">: </LTTextLineHorizontal><LTTextLineHorizontal bbox="[90.024, 591.988, 93.024, 602.704]" height="10.716" width="3.0" word_margin="0.1" x0="90.024" x1="93.024" y0="591.988" y1="602.704"> </LTTextLineHorizontal><LTTextLineHorizontal bbox="[342.07, 578.188, 348.43, 589.096]" height="10.908" width="6.36" word_margin="0.1" x0="342.07" x1="348.43" y0="578.188" y1="589.096">: </LTTextLineHorizontal><LTTextLineHorizontal bbox="[90.024, 578.188, 199.37, 588.904]" height="10.716" width="109.346" word_margin="0.1" x0="90.024" x1="199.37" y0="578.188" y1="588.904">Biopharm Asia, Inc., </LTTextLineHorizontal><LTTextLineHorizontal bbox="[342.07, 564.388, 504.82, 575.296]" height="10.908" width="162.75" word_margin="0.1" x0="342.07" x1="504.82" y0="564.388" y1="575.296">: ORDER OF SUSPENSION </LTTextLineHorizontal><LTTextLineHorizontal bbox="[90.024, 564.388, 280.49, 575.104]" height="10.716" width="190.466" word_margin="0.1" x0="90.024" x1="280.49" y0="564.388" y1="575.104">China Organic Agriculture, Inc. and </LTTextLineHorizontal><LTTextLineHorizontal bbox="[342.07, 550.588, 439.75, 561.496]" height="10.908" width="97.68" word_margin="0.1" x0="342.07" x1="439.75" y0="550.588" y1="561.496">: OF TRADING </LTTextLineHorizontal><LTTextLineHorizontal bbox="[90.024, 550.588, 185.06, 561.304]" height="10.716" width="95.036" word_margin="0.1" x0="90.024" x1="185.06" y0="550.588" y1="561.304">Guilin Paper, Inc. </LTTextLineHorizontal><LTTextLineHorizontal bbox="[342.07, 536.788, 348.43, 547.696]" height="10.908" width="6.36" word_margin="0.1" x0="342.07" x1="348.43" y0="536.788" y1="547.696">: </LTTextLineHorizontal><LTTextLineHorizontal bbox="[90.024, 536.788, 93.024, 547.504]" height="10.716" width="3.0" word_margin="0.1" x0="90.024" x1="93.024" y0="536.788" y1="547.504"> </LTTextLineHorizontal><LTTextLineHorizontal bbox="[342.07, 522.958, 348.43, 533.866]" height="10.908" width="6.36" word_margin="0.1" x0="342.07" x1="348.43" y0="522.958" y1="533.866">: </LTTextLineHorizontal><LTTextLineHorizontal bbox="[90.024, 522.958, 164.06, 533.674]" height="10.716" width="74.036" word_margin="0.1" x0="90.024" x1="164.06" y0="522.958" y1="533.674">File No. 500-1 </LTTextLineHorizontal><LTTextLineHorizontal bbox="[90.024, 509.158, 348.43, 520.066]" height="10.908" width="258.406" word_margin="0.1" x0="90.024" x1="348.43" y0="509.158" y1="520.066">__________________________________________: </LTTextLineHorizontal><LTTextLineHorizontal bbox="[90.024, 495.358, 93.024, 506.266]" height="10.908" width="3.0" word_margin="0.1" x0="90.024" x1="93.024" y0="495.358" y1="506.266"> </LTTextLineHorizontal><LTTextLineHorizontal bbox="[414.07, 578.188, 417.07, 588.904]" height="10.716" width="3.0" word_margin="0.1" x0="414.07" x1="417.07" y0="578.188" y1="588.904"><LTTextBoxHorizontal bbox="[414.07, 578.188, 417.07, 588.904]" height="10.716" index="17" width="3.0" x0="414.07" x1="417.07" y0="578.188" y1="588.904"> </LTTextBoxHorizontal></LTTextLineHorizontal><LTTextLineHorizontal bbox="[126.02, 536.788, 129.02, 547.504]" height="10.716" width="3.0" word_margin="0.1" x0="126.02" x1="129.02" y0="536.788" y1="547.504"><LTTextBoxHorizontal bbox="[126.02, 536.788, 129.02, 547.504]" height="10.716" index="18" width="3.0" x0="126.02" x1="129.02" y0="536.788" y1="547.504"> </LTTextBoxHorizontal></LTTextLineHorizontal></LTTextBoxHorizontal>
      <LTTextLineHorizontal bbox="[126.02, 467.758, 494.014, 478.666]" height="10.908" width="367.994" word_margin="0.1" x0="126.02" x1="494.014" y0="467.758" y1="478.666">
        <LTTextBoxHorizontal bbox="[126.02, 467.758, 494.014, 478.666]" height="10.908" index="19" width="367.994" x0="126.02" x1="494.014" y0="467.758" y1="478.666">It appears to the Securities and Exchange Commission that there is a lack of </LTTextBoxHorizontal>
      </LTTextLineHorizontal>
      <LTTextLineHorizontal bbox="[90.024, 440.158, 520.192, 451.066]" height="10.908" width="430.168" word_margin="0.1" x0="90.024" x1="520.192" y0="440.158" y1="451.066">
        <LTTextBoxHorizontal bbox="[90.024, 440.158, 520.192, 451.066]" height="10.908" index="20" width="430.168" x0="90.024" x1="520.192" y0="440.158" y1="451.066">current and accurate information concerning the securities of Biopharm Asia, Inc., China </LTTextBoxHorizontal>
      </LTTextLineHorizontal>
      <LTTextLineHorizontal bbox="[90.024, 412.558, 519.178, 423.466]" height="10.908" width="429.154" word_margin="0.1" x0="90.024" x1="519.178" y0="412.558" y1="423.466">
        <LTTextBoxHorizontal bbox="[90.024, 412.558, 519.178, 423.466]" height="10.908" index="21" width="429.154" x0="90.024" x1="519.178" y0="412.558" y1="423.466">Organic Agriculture, Inc., and Guilin Paper, Inc. because Biopharm Asia, Inc. and China </LTTextBoxHorizontal>
      </LTTextLineHorizontal>
      <LTTextLineHorizontal bbox="[90.024, 384.958, 500.194, 395.866]" height="10.908" width="410.17" word_margin="0.1" x0="90.024" x1="500.194" y0="384.958" y1="395.866">
        <LTTextBoxHorizontal bbox="[90.024, 384.958, 500.194, 395.866]" height="10.908" index="22" width="410.17" x0="90.024" x1="500.194" y0="384.958" y1="395.866">Organic Agriculture, Inc. have not filed any periodic reports for any reporting period </LTTextBoxHorizontal>
      </LTTextLineHorizontal>
      <LTTextLineHorizontal bbox="[90.024, 357.358, 494.59, 368.266]" height="10.908" width="404.566" word_margin="0.1" x0="90.024" x1="494.59" y0="357.358" y1="368.266">
        <LTTextBoxHorizontal bbox="[90.024, 357.358, 494.59, 368.266]" height="10.908" index="23" width="404.566" x0="90.024" x1="494.59" y0="357.358" y1="368.266">subsequent to September 30, 2010, and Guilin Paper, Inc. has not filed any periodic </LTTextBoxHorizontal>
      </LTTextLineHorizontal>
      <LTTextLineHorizontal bbox="[90.024, 329.738, 415.39, 340.646]" height="10.908" width="325.366" word_margin="0.1" x0="90.024" x1="415.39" y0="329.738" y1="340.646">
        <LTTextBoxHorizontal bbox="[90.024, 329.738, 415.39, 340.646]" height="10.908" index="24" width="325.366" x0="90.024" x1="415.39" y0="329.738" y1="340.646">reports for any reporting period subsequent to September 30, 2007. </LTTextBoxHorizontal>
      </LTTextLineHorizontal>
      <LTTextLineHorizontal bbox="[126.02, 302.138, 522.8, 313.046]" height="10.908" width="396.78" word_margin="0.1" x0="126.02" x1="522.8" y0="302.138" y1="313.046">
        <LTTextBoxHorizontal bbox="[126.02, 302.138, 522.8, 313.046]" height="10.908" index="25" width="396.78" x0="126.02" x1="522.8" y0="302.138" y1="313.046">The Commission is of the opinion that the public interest and the protection of the </LTTextBoxHorizontal>
      </LTTextLineHorizontal>
      <LTTextLineHorizontal bbox="[90.024, 274.538, 497.74, 285.446]" height="10.908" width="407.716" word_margin="0.1" x0="90.024" x1="497.74" y0="274.538" y1="285.446">
        <LTTextBoxHorizontal bbox="[90.024, 274.538, 497.74, 285.446]" height="10.908" index="26" width="407.716" x0="90.024" x1="497.74" y0="274.538" y1="285.446">investors require a suspension of trading in securities of the above-listed companies. </LTTextBoxHorizontal>
      </LTTextLineHorizontal>
      <LTTextLineHorizontal bbox="[90.024, 246.938, 93.024, 257.846]" height="10.908" width="3.0" word_margin="0.1" x0="90.024" x1="93.024" y0="246.938" y1="257.846">
        <LTTextBoxHorizontal bbox="[90.024, 246.938, 93.024, 257.846]" height="10.908" index="27" width="3.0" x0="90.024" x1="93.024" y0="246.938" y1="257.846"> </LTTextBoxHorizontal>
      </LTTextLineHorizontal>
      <LTTextLineHorizontal bbox="[126.02, 246.938, 518.756, 257.846]" height="10.908" width="392.736" word_margin="0.1" x0="126.02" x1="518.756" y0="246.938" y1="257.846">
        <LTTextBoxHorizontal bbox="[126.02, 246.938, 518.756, 257.846]" height="10.908" index="28" width="392.736" x0="126.02" x1="518.756" y0="246.938" y1="257.846">Therefore, it is ordered, pursuant to Section 12(k) of the Securities Exchange Act </LTTextBoxHorizontal>
      </LTTextLineHorizontal>
      <LTTextLineHorizontal bbox="[90.024, 219.338, 514.564, 230.246]" height="10.908" width="424.54" word_margin="0.1" x0="90.024" x1="514.564" y0="219.338" y1="230.246">
        <LTTextBoxHorizontal bbox="[90.024, 219.338, 514.564, 230.246]" height="10.908" index="29" width="424.54" x0="90.024" x1="514.564" y0="219.338" y1="230.246">of 1934, that trading in the securities of the above-listed companies is suspended for the </LTTextBoxHorizontal>
      </LTTextLineHorizontal>
      <LTTextLineHorizontal bbox="[90.024, 191.738, 516.1, 202.646]" height="10.908" width="426.076" word_margin="0.1" x0="90.024" x1="516.1" y0="191.738" y1="202.646">
        <LTTextBoxHorizontal bbox="[90.024, 191.738, 516.1, 202.646]" height="10.908" index="30" width="426.076" x0="90.024" x1="516.1" y0="191.738" y1="202.646">period from 9:30 a.m. EDT, April 19, 2013, through 11:59 p.m. EDT, on May 2, 2013. </LTTextBoxHorizontal>
      </LTTextLineHorizontal>
      <LTTextLineHorizontal bbox="[90.024, 164.108, 99.024, 175.016]" height="10.908" width="9.0" word_margin="0.1" x0="90.024" x1="99.024" y0="164.108" y1="175.016">
        <LTTextBoxHorizontal bbox="[90.024, 164.108, 99.024, 175.016]" height="10.908" index="31" width="9.0" x0="90.024" x1="99.024" y0="164.108" y1="175.016"> </LTTextBoxHorizontal>
      </LTTextLineHorizontal>
      <LTTextLineHorizontal bbox="[126.02, 164.108, 227.45, 175.016]" height="10.908" width="101.43" word_margin="0.1" x0="126.02" x1="227.45" y0="164.108" y1="175.016">
        <LTTextBoxHorizontal bbox="[126.02, 164.108, 227.45, 175.016]" height="10.908" index="32" width="101.43" x0="126.02" x1="227.45" y0="164.108" y1="175.016">By the Commission. </LTTextBoxHorizontal>
      </LTTextLineHorizontal>
      <LTTextBoxHorizontal bbox="[126.02, 81.312, 129.02, 106.02]" height="24.708" index="33" width="3.0" x0="126.02" x1="129.02" y0="81.312" y1="106.02">
        <LTTextLineHorizontal bbox="[126.02, 95.112, 129.02, 106.02]" height="10.908" width="3.0" word_margin="0.1" x0="126.02" x1="129.02" y0="95.112" y1="106.02"> </LTTextLineHorizontal>
        <LTTextLineHorizontal bbox="[126.02, 81.312, 129.02, 92.22]" height="10.908" width="3.0" word_margin="0.1" x0="126.02" x1="129.02" y0="81.312" y1="92.22"> </LTTextLineHorizontal>
      </LTTextBoxHorizontal>
      <LTTextBoxHorizontal bbox="[162.02, 81.312, 165.02, 106.02]" height="24.708" index="34" width="3.0" x0="162.02" x1="165.02" y0="81.312" y1="106.02">
        <LTTextLineHorizontal bbox="[162.02, 95.112, 165.02, 106.02]" height="10.908" width="3.0" word_margin="0.1" x0="162.02" x1="165.02" y0="95.112" y1="106.02"> </LTTextLineHorizontal>
        <LTTextLineHorizontal bbox="[162.02, 81.312, 165.02, 92.22]" height="10.908" width="3.0" word_margin="0.1" x0="162.02" x1="165.02" y0="81.312" y1="92.22"> </LTTextLineHorizontal>
      </LTTextBoxHorizontal>
      <LTTextBoxHorizontal bbox="[198.05, 81.312, 201.05, 106.02]" height="24.708" index="35" width="3.0" x0="198.05" x1="201.05" y0="81.312" y1="106.02">
        <LTTextLineHorizontal bbox="[198.05, 95.112, 201.05, 106.02]" height="10.908" width="3.0" word_margin="0.1" x0="198.05" x1="201.05" y0="95.112" y1="106.02"> </LTTextLineHorizontal>
        <LTTextLineHorizontal bbox="[198.05, 81.312, 201.05, 92.22]" height="10.908" width="3.0" word_margin="0.1" x0="198.05" x1="201.05" y0="81.312" y1="92.22"> </LTTextLineHorizontal>
      </LTTextBoxHorizontal>
      <LTTextBoxHorizontal bbox="[234.05, 81.312, 237.05, 106.02]" height="24.708" index="36" width="3.0" x0="234.05" x1="237.05" y0="81.312" y1="106.02">
        <LTTextLineHorizontal bbox="[234.05, 95.112, 237.05, 106.02]" height="10.908" width="3.0" word_margin="0.1" x0="234.05" x1="237.05" y0="95.112" y1="106.02"> </LTTextLineHorizontal>
        <LTTextLineHorizontal bbox="[234.05, 81.312, 237.05, 92.22]" height="10.908" width="3.0" word_margin="0.1" x0="234.05" x1="237.05" y0="81.312" y1="92.22"> </LTTextLineHorizontal>
      </LTTextBoxHorizontal>
      <LTTextBoxHorizontal bbox="[270.05, 81.312, 273.05, 106.02]" height="24.708" index="37" width="3.0" x0="270.05" x1="273.05" y0="81.312" y1="106.02">
        <LTTextLineHorizontal bbox="[270.05, 95.112, 273.05, 106.02]" height="10.908" width="3.0" word_margin="0.1" x0="270.05" x1="273.05" y0="95.112" y1="106.02"> </LTTextLineHorizontal>
        <LTTextLineHorizontal bbox="[270.05, 81.312, 273.05, 92.22]" height="10.908" width="3.0" word_margin="0.1" x0="270.05" x1="273.05" y0="81.312" y1="92.22"> </LTTextLineHorizontal>
      </LTTextBoxHorizontal>
      <LTTextBoxHorizontal bbox="[306.05, 81.312, 309.05, 106.02]" height="24.708" index="38" width="3.0" x0="306.05" x1="309.05" y0="81.312" y1="106.02">
        <LTTextLineHorizontal bbox="[306.05, 95.112, 309.05, 106.02]" height="10.908" width="3.0" word_margin="0.1" x0="306.05" x1="309.05" y0="95.112" y1="106.02"> </LTTextLineHorizontal>
        <LTTextLineHorizontal bbox="[306.05, 81.312, 309.05, 92.22]" height="10.908" width="3.0" word_margin="0.1" x0="306.05" x1="309.05" y0="81.312" y1="92.22"> </LTTextLineHorizontal>
      </LTTextBoxHorizontal>
      <LTTextBoxHorizontal bbox="[342.07, 81.312, 437.35, 106.02]" height="24.708" index="39" width="95.28" x0="342.07" x1="437.35" y0="81.312" y1="106.02">
        <LTTextLineHorizontal bbox="[342.07, 95.112, 420.79, 106.02]" height="10.908" width="78.72" word_margin="0.1" x0="342.07" x1="420.79" y0="95.112" y1="106.02">Jill M. Peterson </LTTextLineHorizontal>
        <LTTextLineHorizontal bbox="[342.07, 81.312, 437.35, 92.22]" height="10.908" width="95.28" word_margin="0.1" x0="342.07" x1="437.35" y0="81.312" y1="92.22">Assistant Secretary </LTTextLineHorizontal>
      </LTTextBoxHorizontal>
      <LTTextLineVertical bbox="[90.024, 95.112, 93.024, 147.416]" height="52.304" width="3.0" word_margin="0.1" x0="90.024" x1="93.024" y0="95.112" y1="147.416">
        <LTTextBoxVertical bbox="[90.024, 95.112, 93.024, 147.416]" height="52.304" index="40" width="3.0" x0="90.024" x1="93.024" y0="95.112" y1="147.416"> </LTTextBoxVertical>
      </LTTextLineVertical>
      <LTTextLineHorizontal bbox="[90.024, 81.312, 93.024, 92.22]" height="10.908" width="3.0" word_margin="0.1" x0="90.024" x1="93.024" y0="81.312" y1="92.22">
        <LTTextBoxHorizontal bbox="[90.024, 81.312, 93.024, 92.22]" height="10.908" index="41" width="3.0" x0="90.024" x1="93.024" y0="81.312" y1="92.22"> </LTTextBoxHorizontal>
      </LTTextLineHorizontal>
    </LTFigure>
  </LTPage>
</pdfxml>
